my_package/__init__.py
my_package/b.py
algori-1.0.3.dist-info/LICENSE
algori-1.0.3.dist-info/METADATA
algori-1.0.3.dist-info/WHEEL
algori-1.0.3.dist-info/top_level.txt
algori-1.0.3.dist-info/RECORD
